eight_track_recorder/__init__.py
eight_track_recorder/download_mixes.py
eight_track_recorder/download_tracklists.py
eight_track_recorder/download_users.py
eight_track_recorder/main.py
eight_track_recorder-0.0.1.dist-info/LICENSE
eight_track_recorder-0.0.1.dist-info/WHEEL
eight_track_recorder-0.0.1.dist-info/METADATA
eight_track_recorder-0.0.1.dist-info/RECORD
